fnattr/extra/__init__.py
fnattr/extra/danname.py
fnattr/extra/fnaffle.py
fnattr/extra/make_isbn_ranges.py
fnattr/extra/tellico_sqlite3_rename.py
fnattr/fna/__init__.py
fnattr/util/__init__.py
fnattr/util/checksum.py
fnattr/util/config.py
fnattr/util/docsplit.py
fnattr/util/duration.py
fnattr/util/error.py
fnattr/util/escape.py
fnattr/util/fearmat.py
fnattr/util/io.py
fnattr/util/log.py
fnattr/util/multimap.py
fnattr/util/nested.py
fnattr/util/pytestutil.py
fnattr/util/registry.py
fnattr/util/repr.py
fnattr/util/sqlite.py
fnattr/util/typecheck.py
fnattr/vlju/__init__.py
fnattr/vlju/testutil.py
fnattr/vlju/types/__init__.py
fnattr/vlju/types/all.py
fnattr/vlju/types/doi/__init__.py
fnattr/vlju/types/doi/org.py
fnattr/vlju/types/ean/__init__.py
fnattr/vlju/types/ean/isbn.py
fnattr/vlju/types/ean/isbn_ranges.py
fnattr/vlju/types/ean/ismn.py
fnattr/vlju/types/ean/issn.py
fnattr/vlju/types/file/__init__.py
fnattr/vlju/types/info/__init__.py
fnattr/vlju/types/info/kinds.py
fnattr/vlju/types/lccn/__init__.py
fnattr/vlju/types/site/__init__.py
fnattr/vlju/types/timestamp/__init__.py
fnattr/vlju/types/uri/__init__.py
fnattr/vlju/types/url/__init__.py
fnattr/vlju/types/urn/__init__.py
fnattr/vlju/types/urn/kinds.py
fnattr/vljum/__init__.py
fnattr/vljum/m.py
fnattr/vljum/runner.py
fnattr/vljumap/__init__.py
fnattr/vljumap/enc.py
fnattr/vljumap/factory.py
fnattr-0.2.10.dist-info/licenses/LICENSE
fnattr-0.2.10.dist-info/METADATA
fnattr-0.2.10.dist-info/WHEEL
fnattr-0.2.10.dist-info/entry_points.txt
fnattr-0.2.10.dist-info/top_level.txt
fnattr-0.2.10.dist-info/RECORD
